[
  {
    "filename": "2025-06-11-youtube-example.md",
    "path": "_posts/2025-06-11-youtube-example.md",
    "lastModified": "2025-09-01T07:06:20.963Z",
    "size": 890
  },
  {
    "filename": "2025-06-11-new-system-announcement.md",
    "path": "_posts/2025-06-11-new-system-announcement.md",
    "lastModified": "2025-09-01T07:06:20.963Z",
    "size": 1372
  },
  {
    "filename": "2025-06-11-image-example.md",
    "path": "_posts/2025-06-11-image-example.md",
    "lastModified": "2025-09-01T07:06:20.963Z",
    "size": 952
  },
  {
    "filename": "2025-06-10-sample-post-1.md",
    "path": "_posts/2025-06-10-sample-post-1.md",
    "lastModified": "2025-09-01T07:06:20.963Z",
    "size": 762
  },
  {
    "filename": "2025-06-07-youtube-video.md",
    "path": "_posts/2025-06-07-youtube-video.md",
    "lastModified": "2025-09-01T07:06:20.963Z",
    "size": 1033
  }
]